module/__init__.py
module/core.py
cc_package_xyz_123-0.0.1.dist-info/LICENSE
cc_package_xyz_123-0.0.1.dist-info/METADATA
cc_package_xyz_123-0.0.1.dist-info/WHEEL
cc_package_xyz_123-0.0.1.dist-info/top_level.txt
cc_package_xyz_123-0.0.1.dist-info/RECORD
