Metadata-Version: 2.1
Name: cc_package_xyz_123
Version: 0.0.1
Summary: package test
Author: cc
Author-email: cc@qq.com
Requires-Python: >=3.6
License-File: LICENSE
